{"metadata": {"dbt_schema_version": "https://schemas.getdbt.com/dbt/sources/v3.json", "dbt_version": "1.2.3", "generated_at": "2023-01-02T12:23:12.816840Z", "invocation_id": "5cc7b0d4-5e2d-4f3e-bd5d-ebc9d7d0899c", "env": {}}, "results": [{"unique_id": "source.dbtlearn.airbnb.reviews", "max_loaded_at": "2022-12-30T07:41:12.007000+00:00", "snapshotted_at": "2023-01-02T12:23:12.053000+00:00", "max_loaded_at_time_ago_in_s": 276120.046, "status": "error", "criteria": {"warn_after": {"count": 1, "period": "hour"}, "error_after": {"count": 24, "period": "hour"}, "filter": null}, "adapter_response": {}, "timing": [{"name": "compile", "started_at": "2023-01-02T12:23:11.563493Z", "completed_at": "2023-01-02T12:23:11.563493Z"}, {"name": "execute", "started_at": "2023-01-02T12:23:11.564493Z", "completed_at": "2023-01-02T12:23:12.806504Z"}], "thread_id": "Thread-1 (worker)", "execution_time": 1.245931625366211}], "elapsed_time": 2.2357211112976074}